{"TITULO":"ray","TEXTO":"%%%%%%%%%","AUTOR": "23432"},
{"TITULO":"5","TEXTO":"5","AUTOR": ""},
{"TITULO":"top","TEXTO":"top","AUTOR": "ray"},
{"TITULO":"Ficar no topo","TEXTO":"123","AUTOR": "ray"}
,{"TITULO":"Artigo muito legal","TEXTO":"exemplo 001","AUTOR": "RAY"}
,{"TITULO":"123","TEXTO":"rasdsdfds ","AUTOR": "ray"}
,{"TITULO":"teste","TEXTO":"123","AUTOR": "ray"}
,{"TITULO":"novo artigo","TEXTO":"exemplo","AUTOR": "ray"}
,{"TITULO":"novo 2020","TEXTO":"qwe","AUTOR": "ray"}
,{"TITULO":"123","TEXTO":"123","AUTOR": "ray"}
,{"TITULO":"ray","TEXTO":"123","AUTOR": "ray"}
